geneve/README.md
geneve/__init__.py
geneve/config.py
geneve/constraints.py
geneve/events_emitter.py
geneve/events_emitter_eql.py
geneve/kql/__init__.py
geneve/kql/ast.py
geneve/kql/dsl.py
geneve/kql/eql2kql.py
geneve/kql/errors.py
geneve/kql/evaluator.py
geneve/kql/kql.g
geneve/kql/kql2eql.py
geneve/kql/optimizer.py
geneve/kql/parser.py
geneve/solver/__init__.py
geneve/solver/group_as.py
geneve/solver/group_azure.py
geneve/solver/group_event.py
geneve/solver/group_geo.py
geneve/solver/type_boolean.py
geneve/solver/type_date.py
geneve/solver/type_geo_point.py
geneve/solver/type_ip.py
geneve/solver/type_keyword.py
geneve/solver/type_long.py
geneve/utils/__init__.py
geneve/utils/ast_dag.py
geneve/utils/dirs.py
geneve/utils/epr.py
geneve/utils/hdict.py
geneve/utils/kibana.py
geneve/utils/shelllib.py
geneve/utils/solution_space.py
geneve-0.3.0.dist-info/LICENSE.txt
geneve-0.3.0.dist-info/METADATA
geneve-0.3.0.dist-info/WHEEL
geneve-0.3.0.dist-info/top_level.txt
geneve-0.3.0.dist-info/RECORD
