Metadata-Version: 2.1
Name: geneve
Version: 0.3.0
Summary: Generate data from data models
Author-email: Domenico Andreoli <domenico.andreoli@elastic.co>
License: 
Project-URL: Homepage, https://github.com/elastic/geneve
Project-URL: Bug Tracker, https://github.com/elastic/geneve/issues
Keywords: data,test,mock,generator
Classifier: License :: OSI Approved :: Apache Software License
Classifier: Programming Language :: Python
Classifier: Topic :: Software Development :: Libraries :: Python Modules
Classifier: Topic :: Software Development :: Quality Assurance
Classifier: Topic :: Software Development :: Testing
Requires-Python: >=3.8
License-File: LICENSE.txt
Requires-Dist: elasticsearch >=8.2.0
Requires-Dist: eql ==0.9.19
Requires-Dist: faker
Requires-Dist: faker-datasets
Requires-Dist: infinite-sets
Requires-Dist: pytoml
Requires-Dist: requests
Requires-Dist: ruamel.yaml
